src/__init__.py
src/application/__init__.py
src/application/application_alert_config.py
src/application/application_analyze.py
src/application/application_catalog.py
src/application/application_global_alert_config.py
src/application/application_metrics.py
src/application/application_resources.py
src/application/application_settings.py
src/application/application_topology.py
src/automation/action_catalog.py
src/automation/action_history.py
src/core/__init__.py
src/core/server.py
src/core/utils.py
src/event/__init__.py
src/event/events_tools.py
src/infrastructure/__init__.py
src/infrastructure/infrastructure_analyze.py
src/infrastructure/infrastructure_catalog.py
src/infrastructure/infrastructure_metrics.py
src/infrastructure/infrastructure_resources.py
src/infrastructure/infrastructure_topology.py
src/log/__init__.py
src/log/log_alert_configuration.py
src/prompts/__init__.py
src/prompts/application/__init__.py
src/prompts/application/application_alerts.py
src/prompts/application/application_catalog.py
src/prompts/application/application_metrics.py
src/prompts/application/application_resources.py
src/prompts/application/application_settings.py
src/prompts/application/application_topology.py
src/prompts/events/__init__.py
src/prompts/events/events_tools.py
src/prompts/infrastructure/infrastructure_analyze.py
src/prompts/infrastructure/infrastructure_catalog.py
src/prompts/infrastructure/infrastructure_metrics.py
src/prompts/infrastructure/infrastructure_resources.py
src/prompts/infrastructure/infrastructure_topology.py
src/prompts/settings/__init__.py
src/prompts/settings/custom_dashboard.py
src/prompts/website/__init__.py
src/prompts/website/website_analyze.py
src/prompts/website/website_catalog.py
src/prompts/website/website_configuration.py
src/prompts/website/website_metrics.py
src/settings/__init__.py
src/settings/custom_dashboard_tools.py
src/website/__init__.py
src/website/website_analyze.py
src/website/website_catalog.py
src/website/website_configuration.py
mcp_instana-0.3.1.dist-info/METADATA
mcp_instana-0.3.1.dist-info/WHEEL
mcp_instana-0.3.1.dist-info/entry_points.txt
mcp_instana-0.3.1.dist-info/licenses/LICENSE.md
mcp_instana-0.3.1.dist-info/RECORD
