Metadata-Version: 2.4
Name: mcp-instana
Version: 0.3.1
Summary: MCP server for Instana
Author-email: Elina Priyadarshinee <Elina.priyadarshinee1@ibm.com>, Guangya Liu <gyliu@ibm.com>, Isabell Sippli <ischwert@de.ibm.com>, Jay Sharma <Jay.Sharma3@ibm.com>, Madhu Tadiparthi <madhu.tadiparthi@ibm.com>, Riya Kumari <Riya.Kumari3@ibm.com>
License: Apache-2.0
License-File: LICENSE.md
Requires-Python: >=3.10
Requires-Dist: fastmcp==2.10.3
Requires-Dist: instana-client==1.0.1
Requires-Dist: mcp
Requires-Dist: pydantic==2.11.7
Requires-Dist: python-dotenv==1.1.0
Requires-Dist: requests==2.32.4
Provides-Extra: dev
Requires-Dist: coverage>=7.10.1; extra == 'dev'
Requires-Dist: pytest-asyncio>=1.1.0; extra == 'dev'
Requires-Dist: pytest-cov>=6.2.1; extra == 'dev'
Requires-Dist: pytest-mock>=3.14.1; extra == 'dev'
Requires-Dist: pytest>=8.4.1; extra == 'dev'
Requires-Dist: ruff==0.5.0; extra == 'dev'
Requires-Dist: uv==0.8.6; extra == 'dev'
